{
  "aggregate": {
    "V1": {
      "n_signals": 303,
      "n_filled": 262,
      "n_tp": 185,
      "n_sl": 75,
      "n_timeout": 2,
      "wr": 0.7061068702290076,
      "mean_rr": 0.5856481481481455,
      "net_R": 33.34490740740691,
      "per_trade_R": 0.12727063895956836,
      "pf": 1.4445987654320922,
      "losing_months": 6,
      "trading_months": 19,
      "sigs_per_month": 9.03448275862069
    },
    "V2": {
      "n_signals": 451,
      "n_filled": 405,
      "n_tp": 204,
      "n_sl": 190,
      "n_timeout": 11,
      "wr": 0.5037037037037037,
      "mean_rr": 0.585648148148147,
      "net_R": -70.527777777778,
      "per_trade_R": -0.17414266117969876,
      "pf": 0.6288011695906421,
      "losing_months": 7,
      "trading_months": 19,
      "sigs_per_month": 13.96551724137931
    },
    "V3": {
      "n_signals": 3856,
      "n_filled": 3469,
      "n_tp": 1984,
      "n_sl": 1464,
      "n_timeout": 21,
      "wr": 0.5719227443067166,
      "mean_rr": 0.585648148148148,
      "net_R": -302.07407407407436,
      "per_trade_R": -0.08707814184896925,
      "pf": 0.7936652499494028,
      "losing_months": 16,
      "trading_months": 29,
      "sigs_per_month": 119.62068965517241
    },
    "V4": {
      "n_signals": 4159,
      "n_filled": 3731,
      "n_tp": 2169,
      "n_sl": 1539,
      "n_timeout": 23,
      "wr": 0.5813454837845081,
      "mean_rr": 0.5856481481481478,
      "net_R": -268.7291666666674,
      "per_trade_R": -0.07202604306262864,
      "pf": 0.8253871561620094,
      "losing_months": 15,
      "trading_months": 29,
      "sigs_per_month": 128.6551724137931
    }
  },
  "per_month": {
    "V1": {
      "2024-01": {
        "month": "2024-01",
        "n_signals": 0,
        "n_filled": 0,
        "n_tp": 0,
        "n_sl": 0,
        "n_to": 0,
        "sum_rr": 0.0
      },
      "2024-02": {
        "month": "2024-02",
        "n_signals": 1,
        "n_filled": 0,
        "n_tp": 0,
        "n_sl": 0,
        "n_to": 0,
        "sum_rr": 0.0
      },
      "2024-03": {
        "month": "2024-03",
        "n_signals": 1,
        "n_filled": 1,
        "n_tp": 1,
        "n_sl": 0,
        "n_to": 0,
        "sum_rr": 0.5856481481481229
      },
      "2024-04": {
        "month": "2024-04",
        "n_signals": 3,
        "n_filled": 2,
        "n_tp": 1,
        "n_sl": 1,
        "n_to": 0,
        "sum_rr": 0.5856481481481512
      },
      "2024-05": {
        "month": "2024-05",
        "n_signals": 0,
        "n_filled": 0,
        "n_tp": 0,
        "n_sl": 0,
        "n_to": 0,
        "sum_rr": 0.0
      },
      "2024-06": {
        "month": "2024-06",
        "n_signals": 0,
        "n_filled": 0,
        "n_tp": 0,
        "n_sl": 0,
        "n_to": 0,
        "sum_rr": 0.0
      },
      "2024-07": {
        "month": "2024-07",
        "n_signals": 1,
        "n_filled": 0,
        "n_tp": 0,
        "n_sl": 0,
        "n_to": 0,
        "sum_rr": 0.0
      },
      "2024-08": {
        "month": "2024-08",
        "n_signals": 2,
        "n_filled": 2,
        "n_tp": 1,
        "n_sl": 1,
        "n_to": 0,
        "sum_rr": 0.5856481481481207
      },
      "2024-09": {
        "month": "2024-09",
        "n_signals": 0,
        "n_filled": 0,
        "n_tp": 0,
        "n_sl": 0,
        "n_to": 0,
        "sum_rr": 0.0
      },
      "2024-10": {
        "month": "2024-10",
        "n_signals": 0,
        "n_filled": 0,
        "n_tp": 0,
        "n_sl": 0,
        "n_to": 0,
        "sum_rr": 0.0
      },
      "2024-11": {
        "month": "2024-11",
        "n_signals": 1,
        "n_filled": 1,
        "n_tp": 1,
        "n_sl": 0,
        "n_to": 0,
        "sum_rr": 0.5856481481481821
      },
      "2024-12": {
        "month": "2024-12",
        "n_signals": 1,
        "n_filled": 0,
        "n_tp": 0,
        "n_sl": 0,
        "n_to": 0,
        "sum_rr": 0.0
      },
      "2025-01": {
        "month": "2025-01",
        "n_signals": 1,
        "n_filled": 1,
        "n_tp": 0,
        "n_sl": 0,
        "n_to": 1,
        "sum_rr": 0.0
      },
      "2025-02": {
        "month": "2025-02",
        "n_signals": 2,
        "n_filled": 2,
        "n_tp": 2,
        "n_sl": 0,
        "n_to": 0,
        "sum_rr": 1.1712962962963003
      },
      "2025-03": {
        "month": "2025-03",
        "n_signals": 0,
        "n_filled": 0,
        "n_tp": 0,
        "n_sl": 0,
        "n_to": 0,
        "sum_rr": 0.0
      },
      "2025-04": {
        "month": "2025-04",
        "n_signals": 9,
        "n_filled": 6,
        "n_tp": 2,
        "n_sl": 4,
        "n_to": 0,
        "sum_rr": 1.17129629629629
      },
      "2025-05": {
        "month": "2025-05",
        "n_signals": 6,
        "n_filled": 5,
        "n_tp": 4,
        "n_sl": 1,
        "n_to": 0,
        "sum_rr": 2.342592592592597
      },
      "2025-06": {
        "month": "2025-06",
        "n_signals": 1,
        "n_filled": 1,
        "n_tp": 1,
        "n_sl": 0,
        "n_to": 0,
        "sum_rr": 0.585648148148154
      },
      "2025-07": {
        "month": "2025-07",
        "n_signals": 1,
        "n_filled": 0,
        "n_tp": 0,
        "n_sl": 0,
        "n_to": 0,
        "sum_rr": 0.0
      },
      "2025-08": {
        "month": "2025-08",
        "n_signals": 2,
        "n_filled": 1,
        "n_tp": 0,
        "n_sl": 1,
        "n_to": 0,
        "sum_rr": 0.0
      },
      "2025-09": {
        "month": "2025-09",
        "n_signals": 1,
        "n_filled": 1,
        "n_tp": 1,
        "n_sl": 0,
        "n_to": 0,
        "sum_rr": 0.5856481481481712
      },
      "2025-10": {
        "month": "2025-10",
        "n_signals": 36,
        "n_filled": 33,
        "n_tp": 24,
        "n_sl": 9,
        "n_to": 0,
        "sum_rr": 14.055555555555763
      },
      "2025-11": {
        "month": "2025-11",
        "n_signals": 12,
        "n_filled": 10,
        "n_tp": 7,
        "n_sl": 3,
        "n_to": 0,
        "sum_rr": 4.099537037036892
      },
      "2025-12": {
        "month": "2025-12",
        "n_signals": 7,
        "n_filled": 7,
        "n_tp": 3,
        "n_sl": 3,
        "n_to": 1,
        "sum_rr": 1.7569444444444295
      },
      "2026-01": {
        "month": "2026-01",
        "n_signals": 52,
        "n_filled": 44,
        "n_tp": 26,
        "n_sl": 18,
        "n_to": 0,
        "sum_rr": 15.22685185185198
      },
      "2026-02": {
        "month": "2026-02",
        "n_signals": 49,
        "n_filled": 42,
        "n_tp": 31,
        "n_sl": 11,
        "n_to": 0,
        "sum_rr": 18.155092592592535
      },
      "2026-03": {
        "month": "2026-03",
        "n_signals": 69,
        "n_filled": 63,
        "n_tp": 50,
        "n_sl": 13,
        "n_to": 0,
        "sum_rr": 29.282407407406687
      },
      "2026-04": {
        "month": "2026-04",
        "n_signals": 34,
        "n_filled": 30,
        "n_tp": 21,
        "n_sl": 9,
        "n_to": 0,
        "sum_rr": 12.29861111111103
      },
      "2026-05": {
        "month": "2026-05",
        "n_signals": 11,
        "n_filled": 10,
        "n_tp": 9,
        "n_sl": 1,
        "n_to": 0,
        "sum_rr": 5.270833333333499
      }
    },
    "V2": {
      "2024-01": {
        "month": "2024-01",
        "n_signals": 3,
        "n_filled": 3,
        "n_tp": 0,
        "n_sl": 2,
        "n_to": 1,
        "sum_rr": 0.0
      },
      "2024-02": {
        "month": "2024-02",
        "n_signals": 2,
        "n_filled": 1,
        "n_tp": 1,
        "n_sl": 0,
        "n_to": 0,
        "sum_rr": 0.5856481481481415
      },
      "2024-03": {
        "month": "2024-03",
        "n_signals": 6,
        "n_filled": 4,
        "n_tp": 2,
        "n_sl": 1,
        "n_to": 1,
        "sum_rr": 1.171296296296296
      },
      "2024-04": {
        "month": "2024-04",
        "n_signals": 4,
        "n_filled": 4,
        "n_tp": 4,
        "n_sl": 0,
        "n_to": 0,
        "sum_rr": 2.3425925925926143
      },
      "2024-05": {
        "month": "2024-05",
        "n_signals": 0,
        "n_filled": 0,
        "n_tp": 0,
        "n_sl": 0,
        "n_to": 0,
        "sum_rr": 0.0
      },
      "2024-06": {
        "month": "2024-06",
        "n_signals": 6,
        "n_filled": 4,
        "n_tp": 4,
        "n_sl": 0,
        "n_to": 0,
        "sum_rr": 2.342592592592579
      },
      "2024-07": {
        "month": "2024-07",
        "n_signals": 0,
        "n_filled": 0,
        "n_tp": 0,
        "n_sl": 0,
        "n_to": 0,
        "sum_rr": 0.0
      },
      "2024-08": {
        "month": "2024-08",
        "n_signals": 0,
        "n_filled": 0,
        "n_tp": 0,
        "n_sl": 0,
        "n_to": 0,
        "sum_rr": 0.0
      },
      "2024-09": {
        "month": "2024-09",
        "n_signals": 1,
        "n_filled": 1,
        "n_tp": 0,
        "n_sl": 1,
        "n_to": 0,
        "sum_rr": 0.0
      },
      "2024-10": {
        "month": "2024-10",
        "n_signals": 5,
        "n_filled": 5,
        "n_tp": 3,
        "n_sl": 2,
        "n_to": 0,
        "sum_rr": 1.756944444444415
      },
      "2024-11": {
        "month": "2024-11",
        "n_signals": 65,
        "n_filled": 65,
        "n_tp": 24,
        "n_sl": 40,
        "n_to": 1,
        "sum_rr": 14.055555555555554
      },
      "2024-12": {
        "month": "2024-12",
        "n_signals": 98,
        "n_filled": 98,
        "n_tp": 23,
        "n_sl": 69,
        "n_to": 6,
        "sum_rr": 13.469907407407401
      },
      "2025-01": {
        "month": "2025-01",
        "n_signals": 0,
        "n_filled": 0,
        "n_tp": 0,
        "n_sl": 0,
        "n_to": 0,
        "sum_rr": 0.0
      },
      "2025-02": {
        "month": "2025-02",
        "n_signals": 0,
        "n_filled": 0,
        "n_tp": 0,
        "n_sl": 0,
        "n_to": 0,
        "sum_rr": 0.0
      },
      "2025-03": {
        "month": "2025-03",
        "n_signals": 0,
        "n_filled": 0,
        "n_tp": 0,
        "n_sl": 0,
        "n_to": 0,
        "sum_rr": 0.0
      },
      "2025-04": {
        "month": "2025-04",
        "n_signals": 0,
        "n_filled": 0,
        "n_tp": 0,
        "n_sl": 0,
        "n_to": 0,
        "sum_rr": 0.0
      },
      "2025-05": {
        "month": "2025-05",
        "n_signals": 0,
        "n_filled": 0,
        "n_tp": 0,
        "n_sl": 0,
        "n_to": 0,
        "sum_rr": 0.0
      },
      "2025-06": {
        "month": "2025-06",
        "n_signals": 2,
        "n_filled": 1,
        "n_tp": 1,
        "n_sl": 0,
        "n_to": 0,
        "sum_rr": 0.5856481481481319
      },
      "2025-07": {
        "month": "2025-07",
        "n_signals": 3,
        "n_filled": 3,
        "n_tp": 2,
        "n_sl": 1,
        "n_to": 0,
        "sum_rr": 1.17129629629632
      },
      "2025-08": {
        "month": "2025-08",
        "n_signals": 0,
        "n_filled": 0,
        "n_tp": 0,
        "n_sl": 0,
        "n_to": 0,
        "sum_rr": 0.0
      },
      "2025-09": {
        "month": "2025-09",
        "n_signals": 0,
        "n_filled": 0,
        "n_tp": 0,
        "n_sl": 0,
        "n_to": 0,
        "sum_rr": 0.0
      },
      "2025-10": {
        "month": "2025-10",
        "n_signals": 40,
        "n_filled": 33,
        "n_tp": 19,
        "n_sl": 14,
        "n_to": 0,
        "sum_rr": 11.127314814814762
      },
      "2025-11": {
        "month": "2025-11",
        "n_signals": 4,
        "n_filled": 2,
        "n_tp": 1,
        "n_sl": 1,
        "n_to": 0,
        "sum_rr": 0.5856481481481429
      },
      "2025-12": {
        "month": "2025-12",
        "n_signals": 38,
        "n_filled": 32,
        "n_tp": 19,
        "n_sl": 11,
        "n_to": 2,
        "sum_rr": 11.127314814814826
      },
      "2026-01": {
        "month": "2026-01",
        "n_signals": 75,
        "n_filled": 67,
        "n_tp": 43,
        "n_sl": 24,
        "n_to": 0,
        "sum_rr": 25.182870370370253
      },
      "2026-02": {
        "month": "2026-02",
        "n_signals": 56,
        "n_filled": 50,
        "n_tp": 32,
        "n_sl": 18,
        "n_to": 0,
        "sum_rr": 18.74074074074075
      },
      "2026-03": {
        "month": "2026-03",
        "n_signals": 24,
        "n_filled": 18,
        "n_tp": 14,
        "n_sl": 4,
        "n_to": 0,
        "sum_rr": 8.199074074074106
      },
      "2026-04": {
        "month": "2026-04",
        "n_signals": 14,
        "n_filled": 9,
        "n_tp": 8,
        "n_sl": 1,
        "n_to": 0,
        "sum_rr": 4.685185185185134
      },
      "2026-05": {
        "month": "2026-05",
        "n_signals": 5,
        "n_filled": 5,
        "n_tp": 4,
        "n_sl": 1,
        "n_to": 0,
        "sum_rr": 2.3425925925925806
      }
    },
    "V3": {
      "2024-01": {
        "month": "2024-01",
        "n_signals": 122,
        "n_filled": 105,
        "n_tp": 59,
        "n_sl": 45,
        "n_to": 1,
        "sum_rr": 34.55324074074084
      },
      "2024-02": {
        "month": "2024-02",
        "n_signals": 99,
        "n_filled": 88,
        "n_tp": 51,
        "n_sl": 37,
        "n_to": 0,
        "sum_rr": 29.868055555555753
      },
      "2024-03": {
        "month": "2024-03",
        "n_signals": 91,
        "n_filled": 80,
        "n_tp": 43,
        "n_sl": 36,
        "n_to": 1,
        "sum_rr": 25.18287037037025
      },
      "2024-04": {
        "month": "2024-04",
        "n_signals": 100,
        "n_filled": 91,
        "n_tp": 65,
        "n_sl": 26,
        "n_to": 0,
        "sum_rr": 38.067129629629775
      },
      "2024-05": {
        "month": "2024-05",
        "n_signals": 93,
        "n_filled": 81,
        "n_tp": 54,
        "n_sl": 27,
        "n_to": 0,
        "sum_rr": 31.624999999999986
      },
      "2024-06": {
        "month": "2024-06",
        "n_signals": 90,
        "n_filled": 83,
        "n_tp": 44,
        "n_sl": 39,
        "n_to": 0,
        "sum_rr": 25.76851851851849
      },
      "2024-07": {
        "month": "2024-07",
        "n_signals": 64,
        "n_filled": 58,
        "n_tp": 36,
        "n_sl": 19,
        "n_to": 3,
        "sum_rr": 21.083333333333307
      },
      "2024-08": {
        "month": "2024-08",
        "n_signals": 65,
        "n_filled": 60,
        "n_tp": 40,
        "n_sl": 19,
        "n_to": 1,
        "sum_rr": 23.425925925926126
      },
      "2024-09": {
        "month": "2024-09",
        "n_signals": 64,
        "n_filled": 56,
        "n_tp": 35,
        "n_sl": 21,
        "n_to": 0,
        "sum_rr": 20.497685185185155
      },
      "2024-10": {
        "month": "2024-10",
        "n_signals": 286,
        "n_filled": 275,
        "n_tp": 140,
        "n_sl": 132,
        "n_to": 3,
        "sum_rr": 81.99074074074055
      },
      "2024-11": {
        "month": "2024-11",
        "n_signals": 516,
        "n_filled": 512,
        "n_tp": 224,
        "n_sl": 286,
        "n_to": 2,
        "sum_rr": 131.18518518518474
      },
      "2024-12": {
        "month": "2024-12",
        "n_signals": 323,
        "n_filled": 319,
        "n_tp": 128,
        "n_sl": 183,
        "n_to": 8,
        "sum_rr": 74.96296296296289
      },
      "2025-01": {
        "month": "2025-01",
        "n_signals": 42,
        "n_filled": 39,
        "n_tp": 22,
        "n_sl": 17,
        "n_to": 0,
        "sum_rr": 12.884259259259421
      },
      "2025-02": {
        "month": "2025-02",
        "n_signals": 43,
        "n_filled": 35,
        "n_tp": 21,
        "n_sl": 14,
        "n_to": 0,
        "sum_rr": 12.29861111111117
      },
      "2025-03": {
        "month": "2025-03",
        "n_signals": 18,
        "n_filled": 17,
        "n_tp": 12,
        "n_sl": 5,
        "n_to": 0,
        "sum_rr": 7.027777777777867
      },
      "2025-04": {
        "month": "2025-04",
        "n_signals": 24,
        "n_filled": 18,
        "n_tp": 13,
        "n_sl": 5,
        "n_to": 0,
        "sum_rr": 7.613425925926063
      },
      "2025-05": {
        "month": "2025-05",
        "n_signals": 35,
        "n_filled": 29,
        "n_tp": 20,
        "n_sl": 9,
        "n_to": 0,
        "sum_rr": 11.712962962962925
      },
      "2025-06": {
        "month": "2025-06",
        "n_signals": 44,
        "n_filled": 32,
        "n_tp": 18,
        "n_sl": 14,
        "n_to": 0,
        "sum_rr": 10.541666666666506
      },
      "2025-07": {
        "month": "2025-07",
        "n_signals": 160,
        "n_filled": 132,
        "n_tp": 83,
        "n_sl": 49,
        "n_to": 0,
        "sum_rr": 48.608796296296006
      },
      "2025-08": {
        "month": "2025-08",
        "n_signals": 58,
        "n_filled": 51,
        "n_tp": 41,
        "n_sl": 10,
        "n_to": 0,
        "sum_rr": 24.011574074074407
      },
      "2025-09": {
        "month": "2025-09",
        "n_signals": 99,
        "n_filled": 82,
        "n_tp": 47,
        "n_sl": 35,
        "n_to": 0,
        "sum_rr": 27.525462962962816
      },
      "2025-10": {
        "month": "2025-10",
        "n_signals": 247,
        "n_filled": 211,
        "n_tp": 133,
        "n_sl": 78,
        "n_to": 0,
        "sum_rr": 77.89120370370318
      },
      "2025-11": {
        "month": "2025-11",
        "n_signals": 122,
        "n_filled": 104,
        "n_tp": 63,
        "n_sl": 41,
        "n_to": 0,
        "sum_rr": 36.8958333333335
      },
      "2025-12": {
        "month": "2025-12",
        "n_signals": 165,
        "n_filled": 150,
        "n_tp": 95,
        "n_sl": 53,
        "n_to": 2,
        "sum_rr": 55.63657407407455
      },
      "2026-01": {
        "month": "2026-01",
        "n_signals": 235,
        "n_filled": 214,
        "n_tp": 137,
        "n_sl": 77,
        "n_to": 0,
        "sum_rr": 80.23379629629656
      },
      "2026-02": {
        "month": "2026-02",
        "n_signals": 224,
        "n_filled": 192,
        "n_tp": 119,
        "n_sl": 73,
        "n_to": 0,
        "sum_rr": 69.69212962962956
      },
      "2026-03": {
        "month": "2026-03",
        "n_signals": 187,
        "n_filled": 153,
        "n_tp": 99,
        "n_sl": 54,
        "n_to": 0,
        "sum_rr": 57.97916666666651
      },
      "2026-04": {
        "month": "2026-04",
        "n_signals": 141,
        "n_filled": 119,
        "n_tp": 83,
        "n_sl": 36,
        "n_to": 0,
        "sum_rr": 48.60879629629621
      },
      "2026-05": {
        "month": "2026-05",
        "n_signals": 99,
        "n_filled": 83,
        "n_tp": 59,
        "n_sl": 24,
        "n_to": 0,
        "sum_rr": 34.55324074074058
      }
    },
    "V4": {
      "2024-01": {
        "month": "2024-01",
        "n_signals": 122,
        "n_filled": 105,
        "n_tp": 59,
        "n_sl": 45,
        "n_to": 1,
        "sum_rr": 34.55324074074084
      },
      "2024-02": {
        "month": "2024-02",
        "n_signals": 100,
        "n_filled": 88,
        "n_tp": 51,
        "n_sl": 37,
        "n_to": 0,
        "sum_rr": 29.868055555555753
      },
      "2024-03": {
        "month": "2024-03",
        "n_signals": 92,
        "n_filled": 81,
        "n_tp": 44,
        "n_sl": 36,
        "n_to": 1,
        "sum_rr": 25.768518518518373
      },
      "2024-04": {
        "month": "2024-04",
        "n_signals": 103,
        "n_filled": 93,
        "n_tp": 66,
        "n_sl": 27,
        "n_to": 0,
        "sum_rr": 38.65277777777793
      },
      "2024-05": {
        "month": "2024-05",
        "n_signals": 93,
        "n_filled": 81,
        "n_tp": 54,
        "n_sl": 27,
        "n_to": 0,
        "sum_rr": 31.624999999999986
      },
      "2024-06": {
        "month": "2024-06",
        "n_signals": 90,
        "n_filled": 83,
        "n_tp": 44,
        "n_sl": 39,
        "n_to": 0,
        "sum_rr": 25.76851851851849
      },
      "2024-07": {
        "month": "2024-07",
        "n_signals": 65,
        "n_filled": 58,
        "n_tp": 36,
        "n_sl": 19,
        "n_to": 3,
        "sum_rr": 21.083333333333307
      },
      "2024-08": {
        "month": "2024-08",
        "n_signals": 67,
        "n_filled": 62,
        "n_tp": 41,
        "n_sl": 20,
        "n_to": 1,
        "sum_rr": 24.011574074074247
      },
      "2024-09": {
        "month": "2024-09",
        "n_signals": 64,
        "n_filled": 56,
        "n_tp": 35,
        "n_sl": 21,
        "n_to": 0,
        "sum_rr": 20.497685185185155
      },
      "2024-10": {
        "month": "2024-10",
        "n_signals": 286,
        "n_filled": 275,
        "n_tp": 140,
        "n_sl": 132,
        "n_to": 3,
        "sum_rr": 81.99074074074055
      },
      "2024-11": {
        "month": "2024-11",
        "n_signals": 517,
        "n_filled": 513,
        "n_tp": 225,
        "n_sl": 286,
        "n_to": 2,
        "sum_rr": 131.77083333333292
      },
      "2024-12": {
        "month": "2024-12",
        "n_signals": 324,
        "n_filled": 319,
        "n_tp": 128,
        "n_sl": 183,
        "n_to": 8,
        "sum_rr": 74.96296296296289
      },
      "2025-01": {
        "month": "2025-01",
        "n_signals": 43,
        "n_filled": 40,
        "n_tp": 22,
        "n_sl": 17,
        "n_to": 1,
        "sum_rr": 12.884259259259421
      },
      "2025-02": {
        "month": "2025-02",
        "n_signals": 45,
        "n_filled": 37,
        "n_tp": 23,
        "n_sl": 14,
        "n_to": 0,
        "sum_rr": 13.469907407407469
      },
      "2025-03": {
        "month": "2025-03",
        "n_signals": 18,
        "n_filled": 17,
        "n_tp": 12,
        "n_sl": 5,
        "n_to": 0,
        "sum_rr": 7.027777777777867
      },
      "2025-04": {
        "month": "2025-04",
        "n_signals": 33,
        "n_filled": 24,
        "n_tp": 15,
        "n_sl": 9,
        "n_to": 0,
        "sum_rr": 8.784722222222353
      },
      "2025-05": {
        "month": "2025-05",
        "n_signals": 41,
        "n_filled": 34,
        "n_tp": 24,
        "n_sl": 10,
        "n_to": 0,
        "sum_rr": 14.055555555555522
      },
      "2025-06": {
        "month": "2025-06",
        "n_signals": 45,
        "n_filled": 33,
        "n_tp": 19,
        "n_sl": 14,
        "n_to": 0,
        "sum_rr": 11.12731481481466
      },
      "2025-07": {
        "month": "2025-07",
        "n_signals": 161,
        "n_filled": 132,
        "n_tp": 83,
        "n_sl": 49,
        "n_to": 0,
        "sum_rr": 48.608796296296006
      },
      "2025-08": {
        "month": "2025-08",
        "n_signals": 60,
        "n_filled": 52,
        "n_tp": 41,
        "n_sl": 11,
        "n_to": 0,
        "sum_rr": 24.011574074074407
      },
      "2025-09": {
        "month": "2025-09",
        "n_signals": 100,
        "n_filled": 83,
        "n_tp": 48,
        "n_sl": 35,
        "n_to": 0,
        "sum_rr": 28.111111111110986
      },
      "2025-10": {
        "month": "2025-10",
        "n_signals": 283,
        "n_filled": 244,
        "n_tp": 157,
        "n_sl": 87,
        "n_to": 0,
        "sum_rr": 91.94675925925895
      },
      "2025-11": {
        "month": "2025-11",
        "n_signals": 134,
        "n_filled": 114,
        "n_tp": 70,
        "n_sl": 44,
        "n_to": 0,
        "sum_rr": 40.995370370370395
      },
      "2025-12": {
        "month": "2025-12",
        "n_signals": 172,
        "n_filled": 157,
        "n_tp": 98,
        "n_sl": 56,
        "n_to": 3,
        "sum_rr": 57.39351851851898
      },
      "2026-01": {
        "month": "2026-01",
        "n_signals": 287,
        "n_filled": 258,
        "n_tp": 163,
        "n_sl": 95,
        "n_to": 0,
        "sum_rr": 95.46064814814854
      },
      "2026-02": {
        "month": "2026-02",
        "n_signals": 273,
        "n_filled": 234,
        "n_tp": 150,
        "n_sl": 84,
        "n_to": 0,
        "sum_rr": 87.8472222222221
      },
      "2026-03": {
        "month": "2026-03",
        "n_signals": 256,
        "n_filled": 216,
        "n_tp": 149,
        "n_sl": 67,
        "n_to": 0,
        "sum_rr": 87.2615740740732
      },
      "2026-04": {
        "month": "2026-04",
        "n_signals": 175,
        "n_filled": 149,
        "n_tp": 104,
        "n_sl": 45,
        "n_to": 0,
        "sum_rr": 60.90740740740724
      },
      "2026-05": {
        "month": "2026-05",
        "n_signals": 110,
        "n_filled": 93,
        "n_tp": 68,
        "n_sl": 25,
        "n_to": 0,
        "sum_rr": 39.824074074074076
      }
    }
  }
}